retail_dictionary/__init__.py
retail_dictionary/rd.xlsx
retail_dictionary/retail_dictionary.py
retail_dictionary-0.0.2.dist-info/METADATA
retail_dictionary-0.0.2.dist-info/WHEEL
retail_dictionary-0.0.2.dist-info/top_level.txt
retail_dictionary-0.0.2.dist-info/RECORD
