Metadata-Version: 2.1
Name: retail-dictionary
Version: 0.0.2
Summary: Retail Dictionary where you can find meaning of Retail terms
Author: Marcel Tino
Author-email: <marceltino92@gmail.com>
Keywords: retail,retailterms,retaildictionary
Requires-Dist: pandas
Requires-Dist: spacy
